altissimo/__init__.py
altissimo/api.py
altissimo/fastapi.py
altissimo/firestore.py
altissimo/googleapiclient.py
altissimo/secretmanager.py
altissimo/sheets.py
altissimo/storage.py
altissimo/test_api.py
altissimo/test_firestore.py
altissimo/test_googleapiclient.py
altissimo/test_secretmanager.py
altissimo/test_sheets.py
altissimo/test_tools.py
altissimo/tools.py
altissimo-0.1.13.dist-info/LICENSE
altissimo-0.1.13.dist-info/METADATA
altissimo-0.1.13.dist-info/WHEEL
altissimo-0.1.13.dist-info/top_level.txt
altissimo-0.1.13.dist-info/RECORD
